group_testing/__init__.py
group_testing/generate_groups.py
group_testing/generate_individual_status.py
group_testing/generate_test_results.py
group_testing/group_testing.py
group_testing/group_testing_decoder.py
group_testing/group_testing_evaluation.py
group_testing/utils.py
GroupTesting-0.1.0.dist-info/LICENSE
GroupTesting-0.1.0.dist-info/METADATA
GroupTesting-0.1.0.dist-info/WHEEL
GroupTesting-0.1.0.dist-info/entry_points.txt
GroupTesting-0.1.0.dist-info/top_level.txt
GroupTesting-0.1.0.dist-info/RECORD
