Metadata-Version: 2.1
Name: GroupTesting
Version: 0.1.0
Summary: Group testing for SARS-CoV-2 in large populations.
Home-page: https://github.com/WGS-TB/GroupTesting
Author: Hooman Zabeti, Nick Dexter
Author-email: hzabeti@sfu.ca, nicholas_dexter@sfu.ca
License: GPL-3
Platform: UNKNOWN
Requires-Dist: numpy
Requires-Dist: pandas
Requires-Dist: pulp
Requires-Dist: pymprog
Requires-Dist: python-igraph
Requires-Dist: pyyaml
Requires-Dist: scipy
Requires-Dist: sklearn
